bearboto3/__init__.py
bearboto3/dynamodb.py
bearboto3/ec2.py
bearboto3/iam.py
bearboto3/lambda_.py
bearboto3/s3.py
bearboto3/sns.py
bearboto3/sqs.py
bearboto3-0.1.3.dist-info/LICENSE
bearboto3-0.1.3.dist-info/WHEEL
bearboto3-0.1.3.dist-info/METADATA
bearboto3-0.1.3.dist-info/RECORD
