Metadata-Version: 2.1
Name: bearboto3
Version: 0.1.3
Summary: Facilitates using beartype runtime type-checking with the AWS SDK
Home-page: https://github.com/beartype/bearboto3
License: MIT
Keywords: aws,boto3,type checking,type hints,beartype
Author: Paul Hutchings
Author-email: dev@studiop.page
Requires-Python: >=3.7,<4.0
Classifier: Development Status :: 4 - Beta
Classifier: Intended Audience :: Developers
Classifier: License :: OSI Approved :: MIT License
Classifier: Natural Language :: English
Classifier: Operating System :: OS Independent
Classifier: Programming Language :: Python :: 3
Classifier: Programming Language :: Python :: 3 :: Only
Classifier: Programming Language :: Python :: 3.10
Classifier: Programming Language :: Python :: 3.7
Classifier: Programming Language :: Python :: 3.8
Classifier: Programming Language :: Python :: 3.9
Classifier: Topic :: Software Development :: Code Generators
Classifier: Topic :: Software Development :: Libraries :: Python Modules
Classifier: Topic :: Software Development :: Quality Assurance
Classifier: Typing :: Typed
Provides-Extra: dynamodb
Provides-Extra: ec2
Provides-Extra: iam
Provides-Extra: lambda
Provides-Extra: s3
Provides-Extra: sns
Provides-Extra: sqs
Requires-Dist: beartype (>=0.9.0)
Requires-Dist: mypy-boto3-dynamodb (>=1.21.4,<2.0.0); extra == "dynamodb"
Requires-Dist: mypy-boto3-ec2 (>=1.21.1,<2.0.0); extra == "ec2"
Requires-Dist: mypy-boto3-iam (>=1.21.2,<2.0.0); extra == "iam"
Requires-Dist: mypy-boto3-lambda (>=1.21.0,<2.0.0); extra == "lambda"
Requires-Dist: mypy-boto3-s3 (>=1.21.0,<2.0.0); extra == "s3"
Requires-Dist: mypy-boto3-sns (>=1.21.0,<2.0.0); extra == "sns"
Requires-Dist: mypy-boto3-sqs (>=1.21.0,<2.0.0); extra == "sqs"
Requires-Dist: typing-extensions (>=4.2.0,<5.0.0); python_version < "3.9"
Project-URL: Issues, https://github.com/beartype/bearboto3/issues
Project-URL: Repository, https://github.com/beartype/bearboto3
